nylas/__init__.py
nylas/_production_python_version.py
nylas/api/__init__.py
nylas/api/wsgi.py
nylas/logging/__init__.py
nylas/logging/log.py
nylas/logging/sentry/__init__.py
nylas/util/__init__.py
nylas/util/debug.py
nylas_production_python-0.4.2.dist-info/DESCRIPTION.rst
nylas_production_python-0.4.2.dist-info/METADATA
nylas_production_python-0.4.2.dist-info/metadata.json
nylas_production_python-0.4.2.dist-info/RECORD
nylas_production_python-0.4.2.dist-info/top_level.txt
nylas_production_python-0.4.2.dist-info/WHEEL
