Metadata-Version: 2.0
Name: nylas-production-python
Version: 0.4.2
Summary: Nylas production python utilities
Home-page: https://www.nylas.com
Author: Nylas Team
Author-email: team@nylas.com
License: AGPLv3
Keywords: nylas api production
Platform: UNKNOWN
Requires-Dist: raven (>=5.5.0)
Requires-Dist: gevent (>=1.0.1)
Requires-Dist: colorlog (>=1.8)
Requires-Dist: structlog (>=16.1.0)
Requires-Dist: gunicorn (>=19.0.0)
